tamandua-0.0.4.dist-info/METADATA
tamandua-0.0.4.dist-info/WHEEL
tamandua-0.0.4.dist-info/entry_points.txt
tamandua/__init__.py
tamandua/base.py
tamandua/google.py
tamandua-0.0.4.dist-info/RECORD
