Metadata-Version: 2.1
Name: tamandua
Version: 0.0.4
Summary: A tiny web scrapers collection.
Classifier: Programming Language :: Python :: 3
Classifier: License :: OSI Approved :: GNU General Public License v3 or later (GPLv3+)
Classifier: Operating System :: OS Independent
Project-URL: Homepage, https://gitlab.com/andresmrm/tamandua
Project-URL: Issues, https://gitlab.com/andresmrm/tamandua/issues
Requires-Python: >=3.11
Requires-Dist: requests
Requires-Dist: pyrfc6266
Requires-Dist: python-slugify
Requires-Dist: tqdm
